kafka_handler/__init__.py
kafka_python_log_handler-0.0.1.dev12.dist-info/AUTHORS
kafka_python_log_handler-0.0.1.dev12.dist-info/LICENSE
kafka_python_log_handler-0.0.1.dev12.dist-info/METADATA
kafka_python_log_handler-0.0.1.dev12.dist-info/WHEEL
kafka_python_log_handler-0.0.1.dev12.dist-info/pbr.json
kafka_python_log_handler-0.0.1.dev12.dist-info/top_level.txt
kafka_python_log_handler-0.0.1.dev12.dist-info/RECORD
