Metadata-Version: 2.1
Name: kafka-python-log-handler
Version: 0.0.1.dev12
Summary: A log handler for the Python logging module, emitting logs to Kafka topics.
Home-page: https://gitlab.adimian.com/open-source/kafka-log-handler
Author: See AUTHORS
Author-email: contact@adimian.com
License: UNKNOWN
Platform: UNKNOWN
Classifier: Development Status :: 4 - Beta
Classifier: Operating System :: POSIX
Classifier: License :: OSI Approved :: MIT License
Classifier: Programming Language :: Python
Classifier: Programming Language :: Python :: 3.6
Classifier: Programming Language :: Python :: 3.7
Requires-Dist: kafka-python (==1.4.3)
